Metadata-Version: 1.2
Name: glrestore
Version: 1.1.0
Summary: Easily restore objects from AWS glacier from the command line using python
Home-page: https://github.com/MrOlm/glrestore
Author: Matthew Olm
Author-email: mattolm@gmail.com
License: MIT
Platform: UNKNOWN
Requires-Python: >=3.4.0
